pyIPXACT/Catalog.py
pyIPXACT/Component.py
pyIPXACT/Design.py
pyIPXACT/DesignConfiguration.py
pyIPXACT/GeneratorChain.py
pyIPXACT/__init__.py
pyIPXACT-0.1.6.dist-info/LICENSE.md
pyIPXACT-0.1.6.dist-info/METADATA
pyIPXACT-0.1.6.dist-info/WHEEL
pyIPXACT-0.1.6.dist-info/top_level.txt
pyIPXACT-0.1.6.dist-info/RECORD
