Metadata-Version: 2.1
Name: pyIPXACT
Version: 0.1.6
Summary: A Document-Object-Model (DOM) for IP-XACT files.
Home-page: https://github.com/Paebbels/pyIPXACT
Author: Patrick Lehmann
Author-email: Paebbels@gmail.com
License: UNKNOWN
Platform: UNKNOWN
Classifier: License :: OSI Approved :: Apache Software License
Classifier: Operating System :: OS Independent
Classifier: Programming Language :: Python :: 3.5
Classifier: Programming Language :: Python :: 3.6
Classifier: Programming Language :: Python :: 3.7
Classifier: Programming Language :: Python :: 3.8
Classifier: Development Status :: 2 - Pre-Alpha
Classifier: Topic :: Utilities
Requires-Python: >=3.5
